{
  "posts": [
    {
      "author": "Marcelina Skoczek",
      "avatar": "/img/arthur.png",
      "title": "New air routes that promise cheap flights in March!",
      "shareMethod": null
    },
    {
      "author": "Witold Czerwony",
      "avatar": "/img/anna.png",
      "title": "New air routes that promise cheap flights in March!",
      "shareMethod": null
    },
    {
      "author": "Panda Wygodnicka",
      "avatar": "/img/panda.png",
      "title": "New air routes that promise cheap flights in May!",
      "shareMethod": {
        "type": "hashtag",
        "label": "Shared to #discussionaboutanimgttdddgggg"
      },
      "reactions": {
        "likes": 88,
        "shares": 10
      }
    },
    {
      "author": "Piggy Kucyk",
      "avatar": "/img/piggy.png",
      "title": "New air route with cheap flights to Piggy Island!",
      "shareMethod": {
        "type": "weblink",
        "label": "Shared via weblink"
      },
      "reactions": {
        "shares": 357,
        "likes": 24
      }
    }
  ]
}
